aind_watchdog_service/__init__.py
aind_watchdog_service/event_handler.py
aind_watchdog_service/integration_test.py
aind_watchdog_service/main.py
aind_watchdog_service/run_job.py
aind_watchdog_service/icon/watchdog.ico
aind_watchdog_service/icon/watchdog.jpg
aind_watchdog_service/models/__init__.py
aind_watchdog_service/models/manifest_config.py
aind_watchdog_service/models/watch_config.py
aind_watchdog_service-0.1.6.dist-info/METADATA
aind_watchdog_service-0.1.6.dist-info/WHEEL
aind_watchdog_service-0.1.6.dist-info/licenses/LICENSE
aind_watchdog_service-0.1.6.dist-info/RECORD
