Metadata-Version: 2.4
Name: aind-watchdog-service
Version: 0.1.6
Summary: Generated from aind-library-template
Author: Allen Institute for Neural Dynamics
License: MIT
License-File: LICENSE
Classifier: Programming Language :: Python :: 3
Requires-Python: >=3.10
Requires-Dist: aind-data-transfer-service
Requires-Dist: pyyaml
Provides-Extra: dev
Requires-Dist: black; extra == 'dev'
Requires-Dist: bump2version; extra == 'dev'
Requires-Dist: coverage; extra == 'dev'
Requires-Dist: flake8; extra == 'dev'
Requires-Dist: interrogate; extra == 'dev'
Requires-Dist: isort; extra == 'dev'
Provides-Extra: docs
Requires-Dist: autodoc-pydantic; extra == 'docs'
Requires-Dist: furo; extra == 'docs'
Requires-Dist: sphinx; extra == 'docs'
Requires-Dist: sphinx-mdinclude; extra == 'docs'
Provides-Extra: publish
Requires-Dist: pyinstaller==6.2.0; extra == 'publish'
Requires-Dist: setuptools==69.5.1; extra == 'publish'
Provides-Extra: service
Requires-Dist: apscheduler; extra == 'service'
Requires-Dist: crc32c; extra == 'service'
Requires-Dist: mpetk==0.5.2.dev7; extra == 'service'
Requires-Dist: pykeepass>=4.1.0; extra == 'service'
Requires-Dist: requests; extra == 'service'
Requires-Dist: truststore; extra == 'service'
Requires-Dist: watchdog; extra == 'service'
